wy_qcos_client/__init__.py
wy_qcos_client/client.py
wy_qcos_client/shell.py
wy_qcos_client/common/__init__.py
wy_qcos_client/common/args_schema.py
wy_qcos_client/common/client_library.py
wy_qcos_client/common/constant.py
wy_qcos_client/common/errors.py
wy_qcos_client/common/qcos_version.py
wy_qcos_client-1.0.1.data/data/share/wy_qcos_client/samples/qasm/LICENSE
wy_qcos_client-1.0.1.data/data/share/wy_qcos_client/samples/qasm/2.0/adder.qasm
wy_qcos_client-1.0.1.data/data/share/wy_qcos_client/samples/qasm/2.0/bigadder.qasm
wy_qcos_client-1.0.1.data/data/share/wy_qcos_client/samples/qasm/2.0/invalid-qasm.qasm
wy_qcos_client-1.0.1.data/data/share/wy_qcos_client/samples/qasm/2.0/rb.qasm
wy_qcos_client-1.0.1.data/data/share/wy_qcos_client/samples/qasm/2.0/simple-qasm-1-bit.qasm
wy_qcos_client-1.0.1.data/data/share/wy_qcos_client/samples/qasm/2.0/simple-qasm.qasm
wy_qcos_client-1.0.1.data/data/share/wy_qcos_client/samples/qasm/2.0/w-state.qasm
wy_qcos_client-1.0.1.data/data/share/wy_qcos_client/samples/qasm/2.0/benchmark/adder_n118.qasm
wy_qcos_client-1.0.1.data/data/share/wy_qcos_client/samples/qasm/2.0/wirecut/100.qasm
wy_qcos_client-1.0.1.data/data/share/wy_qcos_client/samples/qasm/2.0/wirecut/10_25.qasm
wy_qcos_client-1.0.1.data/data/share/wy_qcos_client/samples/qasm/2.0/wirecut/125.qasm
wy_qcos_client-1.0.1.data/data/share/wy_qcos_client/samples/qasm/2.0/wirecut/12_30.qasm
wy_qcos_client-1.0.1.data/data/share/wy_qcos_client/samples/qasm/2.0/wirecut/150.qasm
wy_qcos_client-1.0.1.data/data/share/wy_qcos_client/samples/qasm/2.0/wirecut/15_35.qasm
wy_qcos_client-1.0.1.data/data/share/wy_qcos_client/samples/qasm/2.0/wirecut/16_80.qasm
wy_qcos_client-1.0.1.data/data/share/wy_qcos_client/samples/qasm/2.0/wirecut/175.qasm
wy_qcos_client-1.0.1.data/data/share/wy_qcos_client/samples/qasm/2.0/wirecut/18_80.qasm
wy_qcos_client-1.0.1.data/data/share/wy_qcos_client/samples/qasm/2.0/wirecut/200_01.qasm
wy_qcos_client-1.0.1.dist-info/licenses/LICENSE
wy_qcos_client-1.0.1.dist-info/METADATA
wy_qcos_client-1.0.1.dist-info/WHEEL
wy_qcos_client-1.0.1.dist-info/entry_points.txt
wy_qcos_client-1.0.1.dist-info/top_level.txt
wy_qcos_client-1.0.1.dist-info/RECORD
