Metadata-Version: 2.4
Name: wy-qcos-client
Version: 1.0.1
Summary: QCOS CLI
Author-email: Zhao Yi <zhaoyi_yewu@cmss.chinamobile.com>, Ji Dalong <jidalong_yewu@cmss.chinamobile.com>, Xu Dong <xudong_yewu@cmss.chinamobile.com>, Wu Fangwei <wufangwei_yewu@cmss.chinamobile.com>, Guo Zhufeng <guozhufeng_yewu@cmss.chinamobile.com>
License:                      木兰宽松许可证, 第2版
Project-URL: Homepage, https://gitee.com/OpenWuYue/qcos
Project-URL: Documentation, https://qcos.readthedocs.io
Project-URL: Changelog, https://gitee.com/OpenWuYue/qcos/blob/develop/CHANGELOG.md
Project-URL: Issue Tracker, https://gitee.com/OpenWuYue/qcos/issues
Project-URL: Source, https://gitee.com/OpenWuYue/qcos
Keywords: qcos,quantum,operating,system
Classifier: Development Status :: 4 - Beta
Classifier: Environment :: Console
Classifier: Natural Language :: English
Classifier: Operating System :: POSIX
Classifier: Operating System :: POSIX :: Linux
Classifier: Programming Language :: Python
Classifier: Programming Language :: Python :: 3
Classifier: Programming Language :: Python :: 3.10
Classifier: Programming Language :: Python :: 3.11
Classifier: Programming Language :: Python :: Implementation :: CPython
Requires-Python: <3.14,>=3.10
License-File: LICENSE
Requires-Dist: argcomplete==3.6.2
Requires-Dist: cliff==4.10.0
Requires-Dist: jsonrpcclient==4.0.3
Requires-Dist: requests==2.32.5
Requires-Dist: schema==0.7.7
Dynamic: license-file
